{
  "variants": {
    "": [
			{ "model": "stars:block/air_decay_1" },
            { "model": "stars:block/air_decay_1", "x": 90 },
            { "model": "stars:block/air_decay_1", "x": 180 },
            { "model": "stars:block/air_decay_1", "x": 270 },
            { "model": "stars:block/air_decay_1", "y": 90 },
            { "model": "stars:block/air_decay_1", "y": 90, "x": 90 },
            { "model": "stars:block/air_decay_1", "y": 90, "x": 180 },
            { "model": "stars:block/air_decay_1", "y": 90, "x": 270 },
            { "model": "stars:block/air_decay_1", "y": 180 },
            { "model": "stars:block/air_decay_1", "y": 180, "x": 90 },
            { "model": "stars:block/air_decay_1", "y": 180, "x": 180 },
            { "model": "stars:block/air_decay_1", "y": 180, "x": 270 },
            { "model": "stars:block/air_decay_1", "y": 270 },
            { "model": "stars:block/air_decay_1", "y": 270, "x": 90 },
            { "model": "stars:block/air_decay_1", "y": 270, "x": 180 },
            { "model": "stars:block/air_decay_1", "y": 270, "x": 270 },
			{ "model": "stars:block/air_decay_2" },
            { "model": "stars:block/air_decay_2", "x": 90 },
            { "model": "stars:block/air_decay_2", "x": 180 },
            { "model": "stars:block/air_decay_2", "x": 270 },
            { "model": "stars:block/air_decay_2", "y": 90 },
            { "model": "stars:block/air_decay_2", "y": 90, "x": 90 },
            { "model": "stars:block/air_decay_2", "y": 90, "x": 180 },
            { "model": "stars:block/air_decay_2", "y": 90, "x": 270 },
            { "model": "stars:block/air_decay_2", "y": 180 },
            { "model": "stars:block/air_decay_2", "y": 180, "x": 90 },
            { "model": "stars:block/air_decay_2", "y": 180, "x": 180 },
            { "model": "stars:block/air_decay_2", "y": 180, "x": 270 },
            { "model": "stars:block/air_decay_2", "y": 270 },
            { "model": "stars:block/air_decay_2", "y": 270, "x": 90 },
            { "model": "stars:block/air_decay_2", "y": 270, "x": 180 },
            { "model": "stars:block/air_decay_2", "y": 270, "x": 270 },
			{ "model": "stars:block/air_decay_3" },
            { "model": "stars:block/air_decay_3", "x": 90 },
            { "model": "stars:block/air_decay_3", "x": 180 },
            { "model": "stars:block/air_decay_3", "x": 270 },
            { "model": "stars:block/air_decay_3", "y": 90 },
            { "model": "stars:block/air_decay_3", "y": 90, "x": 90 },
            { "model": "stars:block/air_decay_3", "y": 90, "x": 180 },
            { "model": "stars:block/air_decay_3", "y": 90, "x": 270 },
            { "model": "stars:block/air_decay_3", "y": 180 },
            { "model": "stars:block/air_decay_3", "y": 180, "x": 90 },
            { "model": "stars:block/air_decay_3", "y": 180, "x": 180 },
            { "model": "stars:block/air_decay_3", "y": 180, "x": 270 },
            { "model": "stars:block/air_decay_3", "y": 270 },
            { "model": "stars:block/air_decay_3", "y": 270, "x": 90 },
            { "model": "stars:block/air_decay_3", "y": 270, "x": 180 },
            { "model": "stars:block/air_decay_3", "y": 270, "x": 270 },
			{ "model": "stars:block/air_decay_4" },
            { "model": "stars:block/air_decay_4", "x": 90 },
            { "model": "stars:block/air_decay_4", "x": 180 },
            { "model": "stars:block/air_decay_4", "x": 270 },
            { "model": "stars:block/air_decay_4", "y": 90 },
            { "model": "stars:block/air_decay_4", "y": 90, "x": 90 },
            { "model": "stars:block/air_decay_4", "y": 90, "x": 180 },
            { "model": "stars:block/air_decay_4", "y": 90, "x": 270 },
            { "model": "stars:block/air_decay_4", "y": 180 },
            { "model": "stars:block/air_decay_4", "y": 180, "x": 90 },
            { "model": "stars:block/air_decay_4", "y": 180, "x": 180 },
            { "model": "stars:block/air_decay_4", "y": 180, "x": 270 },
            { "model": "stars:block/air_decay_4", "y": 270 },
            { "model": "stars:block/air_decay_4", "y": 270, "x": 90 },
            { "model": "stars:block/air_decay_4", "y": 270, "x": 180 },
            { "model": "stars:block/air_decay_4", "y": 270, "x": 270 }
	]
  }
}